fastapi_scaffold/__init__.py
fastapi_scaffold/cli.py
fastapi_scaffold/generator.py
fastapi_scaffold/setup_env.py
fastapi_scaffold/templates/.env.jinja2
fastapi_scaffold/templates/.gitignore.jinja2
fastapi_scaffold/templates/README.md.jinja2
fastapi_scaffold/templates/init_db.py.jinja2
fastapi_scaffold/templates/main.py.jinja2
fastapi_scaffold/templates/module_model.py.jinja2
fastapi_scaffold/templates/module_router.py.jinja2
fastapi_scaffold/templates/module_schema.py.jinja2
fastapi_scaffold/templates/common/base_router.py.jinja2
fastapi_scaffold/templates/common/config.py.jinja2
fastapi_scaffold/templates/common/context.py.jinja2
fastapi_scaffold/templates/common/logger.py.jinja2
fastapi_scaffold/templates/common/utils.py.jinja2
fastapi_scaffold/templates/common/entity/base_response.py.jinja2
fastapi_scaffold/templates/common/entity/schemas/__init__.py.jinja2
fastapi_scaffold/templates/common/entity/schemas/user.py.jinja2
fastapi_scaffold/templates/common/middlewares/log_middleware.py.jinja2
fastapi_scaffold/templates/common/orm/__init__.py.jinja2
fastapi_scaffold/templates/common/orm/base_model.py.jinja2
fastapi_scaffold/templates/common/orm/db.py.jinja2
fastapi_scaffold/templates/models/__init__.py.jinja2
fastapi_scaffold/templates/models/user.py.jinja2
fastapi_scaffold/templates/router/__init__.py.jinja2
fastapi_scaffold/templates/router/user.py.jinja2
simple_fastapi_scaffold-0.1.2.dist-info/METADATA
simple_fastapi_scaffold-0.1.2.dist-info/WHEEL
simple_fastapi_scaffold-0.1.2.dist-info/entry_points.txt
simple_fastapi_scaffold-0.1.2.dist-info/top_level.txt
simple_fastapi_scaffold-0.1.2.dist-info/RECORD
