Metadata-Version: 2.1
Name: simple-fastapi-scaffold
Version: 0.1.2
Summary: UNKNOWN
Home-page: UNKNOWN
License: UNKNOWN
Platform: UNKNOWN
Requires-Python: >=3.9
Requires-Dist: click (>=8.1.0)
Requires-Dist: jinja2 (>=3.1.0)
Requires-Dist: pydantic (>=2.0.0)
Requires-Dist: rich (>=13.0.0)
Requires-Dist: toml (>=0.10.0)
